simpy_ejector/EjectorGeom.py
simpy_ejector/EjectorMixer.py
simpy_ejector/NozzleParams.py
simpy_ejector/__init__.py
simpy_ejector/coolprop_material.py
simpy_ejector/flowSolver.py
simpy_ejector/materialFactory.py
simpy_ejector/matprop_gen.py
simpy_ejector/nozzleFactory.py
simpy_ejector/nozzleSolver.py
simpy_ejector/numSolvers.py
simpy_ejector/refProp.py
simpy_ejector/refprop_material.py
simpy_ejector/charts/Critical_flow.png
simpy_ejector/charts/PressureExp.png
simpy_ejector/charts/PressureProfiles_2phase_Update.png
simpy_ejector/charts/Pressure_profiles_Nozzle.png
simpy_ejector/charts/Pressures_Nozzle_2phase.png
simpy_ejector/charts/R12_ejector.png
simpy_ejector/charts/R12_primnozzle.png
simpy_ejector/charts/ShockInMixer.png
simpy_ejector/charts/chokedButanePNozzle.png
simpy_ejector/charts/getSpeedSound.png
simpy_ejector/useCases/C70sonicPoint.ipynb
simpy_ejector/useCases/CO2Ejector.ipynb
simpy_ejector/useCases/CheckMomint_R1233.py
simpy_ejector/useCases/Compare_R1233zde.py
simpy_ejector/useCases/Dimensioning_R1233zd.py
simpy_ejector/useCases/EjectorButane.py
simpy_ejector/useCases/EjectorHButane.ipynb
simpy_ejector/useCases/EjectorHButane.py
simpy_ejector/useCases/EjectorMixerShocking.ipynb
simpy_ejector/useCases/EjectorMixerSingleShocking.ipynb
simpy_ejector/useCases/EjectorShockinMixer.ipynb
simpy_ejector/useCases/EjectorSingleChoking.ipynb
simpy_ejector/useCases/EjectorWater.py
simpy_ejector/useCases/FrictionChokingAtNozzleExit.ipynb
simpy_ejector/useCases/LavalNozzle1.ipynb
simpy_ejector/useCases/PaperParamsNozzle.ipynb
simpy_ejector/useCases/PolyNozzle_R1233.py
simpy_ejector/useCases/R1233Subcooled.py
simpy_ejector/useCases/R1233Test_Compare.ipynb
simpy_ejector/useCases/R1233Test_Compare.py
simpy_ejector/useCases/R1233Test_Compare2.py
simpy_ejector/useCases/R1233Test_Demo1.ipynb
simpy_ejector/useCases/R1233_Dimensioning.py
simpy_ejector/useCases/R1233zd_backup.ipynb
simpy_ejector/useCases/SuctionMassFR1.ipynb
simpy_ejector/useCases/Untitled.ipynb
simpy_ejector-1.1.0.dist-info/licenses/LICENSE
simpy_ejector-1.1.0.dist-info/METADATA
simpy_ejector-1.1.0.dist-info/WHEEL
simpy_ejector-1.1.0.dist-info/top_level.txt
simpy_ejector-1.1.0.dist-info/RECORD
