Metadata-Version: 2.4
Name: simpy_ejector
Version: 1.1.0
Summary: Ejector 1 dimensional fluid mechanical simulator
Home-page: https://github.com/AdamBuruzs/simpy_ejector
Author: Dr Adam Buruzs
Author-email: adam.buruzs@ait.ac.at
Maintainer: Adam Buruzs
Maintainer-email: aburuzs@gmail.com
Requires-Python: >=3.7
License-File: LICENSE
Requires-Dist: ctREFPROP
Requires-Dist: numpy
Requires-Dist: pandas
Requires-Dist: matplotlib
Requires-Dist: scipy
Requires-Dist: seaborn
Dynamic: author
Dynamic: author-email
Dynamic: description
Dynamic: description-content-type
Dynamic: home-page
Dynamic: license-file
Dynamic: maintainer
Dynamic: maintainer-email
Dynamic: requires-dist
Dynamic: requires-python
Dynamic: summary
